repro_zipfile/__init__.py
repro_zipfile/__init__.pyi
repro_zipfile/py.typed
repro_zipfile-0.4.0.dist-info/METADATA
repro_zipfile-0.4.0.dist-info/WHEEL
repro_zipfile-0.4.0.dist-info/licenses/LICENSE
repro_zipfile-0.4.0.dist-info/RECORD
