Metadata-Version: 2.4
Name: repro-zipfile
Version: 0.4.0
Summary: A tiny, zero-dependency replacement for Python's zipfile.ZipFile for creating reproducible/deterministic ZIP archives.
Project-URL: Documentation, https://github.com/drivendataorg/repro-zipfile#readme
Project-URL: Issues, https://github.com/drivendataorg/repro-zipfile/issues
Project-URL: Source, https://github.com/drivendataorg/repro-zipfile
Author-email: DrivenData <info@drivendata.org>
License: Unless otherwise indicated, this software is copyright of DrivenData and
License-File: LICENSE
Keywords: deterministic,reproducible,zip,zipfile
Classifier: Intended Audience :: Developers
Classifier: Intended Audience :: Science/Research
Classifier: License :: OSI Approved :: MIT License
Classifier: Operating System :: OS Independent
Classifier: Programming Language :: Python
Classifier: Programming Language :: Python :: 3.8
Classifier: Programming Language :: Python :: 3.9
Classifier: Programming Language :: Python :: 3.10
Classifier: Programming Language :: Python :: 3.11
Classifier: Programming Language :: Python :: 3.12
Classifier: Programming Language :: Python :: 3.13
Classifier: Topic :: System :: Archiving
Classifier: Topic :: System :: Archiving :: Compression
Classifier: Topic :: System :: Archiving :: Packaging
Requires-Python: >=3.8
Provides-Extra: cli
Requires-Dist: rpzip; extra == 'cli'
Provides-Extra: tests
Requires-Dist: pytest-cases; extra == 'tests'
Requires-Dist: pytest<8,>=6; extra == 'tests'
